pubpaste.py
pubpaste-0.9.0.dist-info/METADATA
pubpaste-0.9.0.dist-info/WHEEL
pubpaste-0.9.0.dist-info/entry_points.txt
pubpaste-0.9.0.dist-info/top_level.txt
pubpaste-0.9.0.dist-info/RECORD
