Metadata-Version: 2.4
Name: pubpaste
Version: 0.9.0
Author-email: The Anarcat <anarcat@debian.org>
License-Expression: AGPL-3.0-or-later
Project-URL: Homepage, https://gitlab.com/anarcat/pubpaste/
Project-URL: Issues, https://gitlab.com/anarcat/pubpaste/issues
Project-URL: Funding, http://saythanks.io/to/anarcat
Classifier: Development Status :: 4 - Beta
Classifier: Environment :: X11 Applications
Classifier: Intended Audience :: Developers
Classifier: Intended Audience :: System Administrators
Classifier: Operating System :: POSIX
Classifier: Programming Language :: Python :: 3
Classifier: Topic :: Communications :: File Sharing
Requires-Python: >=3.6
